Workbook

Sheet Substation SE Figures
B2: Global constants:
B3: Operating hours per annum | C3: 8000
B4: Workday man-hours | C4: 8
B6: SECTION 1.1: Asset Analysis
B7: System Description | C7: Asset general information and requirements | G7: Repair specifications | J7: Repair costs/year per substation | N7: Service specifications | Q7: Service costs/year per substation | U7: MTCE hours and costs/year | W7: Miscellaneous Costs | AI7: Total Costs
C8: Capability Index | D8: Unit Manufacturing Cost | E8: Assets required per substation | F8: Man-hour rates/hour (repair + service) | G8: MTBF | H8: MTTR | I8: No. of Men/ repair | J8: Avg. Repairs/year | K8: Man-hrs/repair | L8: Avg. Repair hours per year | M8: Avg. Repair cost/year | N8: MTBS | O8: MTTS | P8: No. of Men/ service | Q8: Avg. Services/year | R8: Man-hrs/service | S8: Avg. Service hrs/year | T8: Avg. Service cost/year | U8: Avg. MTCE hrs/year | V8: Avg. MTCE cost/year | W8: Misc. Cost Description | X8: Required for Substation: | AC8: Count | AD8: CAPEX/item | AE8: OPEX/item | AF8: Misc. CAPEX | AG8: Misc. OPEX | AH8: Replacement Cost Notes | AI8: Net CAPEX | AJ8: Net OPEX | AK8: Net LCC
J9: (per substation) | Q9: (per substation) | U9: (per substation) | AF9: (for 5 substations over 40 yrs) | AI9: (for 5 substations over 40 yrs)
C10: CI | D10: £ | F10: £/hour | G10: operating hours | H10: hours | K10: man-hours | L10: man-hours/year | M10: £/year | N10: hours | O10: days | R10: man-hrs | S10: man-hrs/year | T10: £/year | U10: man-hrs/year | V10: £/year | X10: 1 | Y10: 2 | Z10: 3 | AA10: 4 | AB10: 5 | AF10: £ | AH10: (additional costs required to extend lifetime to 42 years) | AI10: £
B11: Rectifier Transformer A | C11: 105 | D11: 300000 | E11: 3 | F11: 75 | G11: 22000 | H11: 3 | I11: 2 | J11: =$C$3/G11 -> 0.36363636 | K11: =H11*I11*E11 -> 18 | L11: =J11*K11 -> 6.5454545 | M11: =L11*F11 -> 490.90909 | N11: 10000 | O11: 3 | P11: 2 | Q11: =$C$3/N11 -> 0.8 | R11: =O11*$C$4*P11*E11 -> 144 | S11: =Q11*R11 -> 115.2 | T11: =S11*F11 -> 8640 | U11: =S11+L11 -> 121.74545 | V11: =T11+M11 -> 9130.9091 | W11: Environmental Improvements for harsh environment | X11: ✓ | AA11: ✓ | AC11: 2 | AD11: 250000 | AE11: 5000 | AF11: =AC11*AD11 -> 500000 | AG11: =AE11*40*AC11 -> 400000 | AH11: Additional £10k required for 2 additional years of OPEX to reach 42 years | AI11: =D11*E11*5+AF11 -> 5000000 | AJ11: =AG11+V11*40*5 -> 2226181.8 | AK11: =AJ11+AI11 -> 7226181.8
B12: Rectifier Transformer B | C12: 140 | D12: 400000 | G12: 32000 | H12: 2 | I12: 2 | J12: =$C$3/G12 -> 0.25 | K12: =H12*I12*E11 -> 12 | L12: =J12*K12 -> 3 | M12: =L12*F11 -> 225 | N12: 25000 | O12: 2 | P12: 2 | Q12: =$C$3/N12 -> 0.32 | R12: =O12*$C$4*P12*E11 -> 96 | S12: =Q12*R12 -> 30.72 | T12: =S12*F11 -> 2304 | U12: =S12+L12 -> 33.72 | V12: =T12+M12 -> 2529 | W12: Crane capacity upgrade required | X12: ✓ | Z12: ✓ | AB12: ✓ | AC12: 3 | AD12: 400000 | AF12: =AC12*AD12 -> 1200000 | AI12: =D12*E11*5+AF12 -> 7200000 | AJ12: =AG12+V12*40*5 -> 505800 | AK12: =AJ12+AI12 -> 7705800
B13: HV Switchboard A | C13: 108 | D13: 375000 | E13: 1 | F13: 75 | G13: 25000 | H13: 3 | I13: 2 | J13: =$C$3/G13 -> 0.32 | K13: =H13*I13*E13 -> 6 | L13: =J13*K13 -> 1.92 | M13: =L13*F13 -> 144 | N13: 17000 | O13: 3 | P13: 2 | Q13: =$C$3/N13 -> 0.47058824 | R13: =O13*$C$4*P13*E13 -> 48 | S13: =Q13*R13 -> 22.588235 | T13: =S13*F13 -> 1694.1176 | U13: =S13+L13 -> 24.508235 | V13: =T13+M13 -> 1838.1176 | W13: Isolating bottle replacement for circuit breaker. 3x bottles/breaker, 8x breakers/substation. Lifetimes: Type A=10yrs, B=15yrs | X13: ✓ | Y13: ✓ | Z13: ✓ | AA13: ✓ | AB13: ✓ | AC13: =3*5*8 -> 120 | AE13: 3000 | AG13: =3*AE13*AC13 -> 1080000 | AH13: 40 years accounted for. Requires additional £360k to extend from 40->50 years (minimum extension) | AI13: =D13*E13*5+AF13 -> 1875000 | AJ13: =AG13+V13*40*5 -> 1447623.5 | AK13: =AJ13+AI13 -> 3322623.5
B14: HV Switchboard B | C14: 140 | D14: 475000 | G14: 30000 | H14: 3.5 | I14: 2 | J14: =$C$3/G14 -> 0.26666667 | K14: =H14*I14*E13 -> 7 | L14: =J14*K14 -> 1.8666667 | M14: =L14*F13 -> 140 | N14: 20000 | O14: 3.5 | P14: 2 | Q14: =$C$3/N14 -> 0.4 | R14: =O14*$C$4*P14*E13 -> 56 | S14: =Q14*R14 -> 22.4 | T14: =S14*F13 -> 1680 | U14: =S14+L14 -> 24.266667 | V14: =T14+M14 -> 1820 | X14: ✓ | Y14: ✓ | Z14: ✓ | AA14: ✓ | AB14: ✓ | AC14: =3*5*8 -> 120 | AE14: 8000 | AG14: =2*AC14*AE14 -> 1920000 | AH14: Due to 15yr lifetime, 45 yrs must be allocated to meet 40 yr requirement. Thus operational for more than 42 years. | AI14: =D14*E13*5+AF14 -> 2375000 | AJ14: =AG14+V14*40*5 -> 2284000 | AK14: =AJ14+AI14 -> 4659000
B15: DC Switchboard A | C15: 120 | D15: 390000 | E15: 1 | F15: 75 | G15: 5000 | H15: 2 | I15: 1 | J15: =$C$3/G15 -> 1.6 | K15: =H15*I15*E15 -> 2 | L15: =J15*K15 -> 3.2 | M15: =L15*F15 -> 240 | N15: 16000 | O15: 2 | P15: 3 | Q15: =$C$3/N15 -> 0.5 | R15: =O15*$C$4*P15*E15 -> 48 | S15: =Q15*R15 -> 24 | T15: =S15*F15 -> 1800 | U15: =S15+L15 -> 27.2 | V15: =T15+M15 -> 2040 | W15: Limited by no. of overload trips. Expected 50 overload trips/yr. 4x/substation. Type: A=150trips, B=200 trips | X15: ✓ | Y15: ✓ | Z15: ✓ | AA15: ✓ | AB15: ✓ | AC15: 20 | AE15: 2500 | AG15: =13*AE15*AC15 -> 650000 | AH15: Due to 3-year lifetime, 42 years are allocated by default to meet 40 year lifecycle requirement. | AI15: =D15*E15*5+AF15 -> 1950000 | AJ15: =AG15+V15*40*5 -> 1058000 | AK15: =AJ15+AI15 -> 3008000
B16: DC Switchboard B | C16: 130 | D16: 450000 | G16: 8000 | H16: 1.5 | I16: 1 | J16: =$C$3/G16 -> 1 | K16: =H16*I16*E15 -> 1.5 | L16: =J16*K16 -> 1.5 | M16: =L16*F15 -> 112.5 | N16: 20000 | O16: 1.5 | P16: 4 | Q16: =$C$3/N16 -> 0.4 | R16: =O16*$C$4*P16*E15 -> 48 | S16: =Q16*R16 -> 19.2 | T16: =S16*F15 -> 1440 | U16: =S16+L16 -> 20.7 | V16: =T16+M16 -> 1552.5 | X16: ✓ | Y16: ✓ | Z16: ✓ | AA16: ✓ | AB16: ✓ | AC16: 20 | AE16: 2500 | AG16: =9*AE16*AC16 -> 450000 | AH16: 40 years allocated by default. Requires £50k in OPEX to extend to 44 years. | AI16: =D16*E15*5+AF16 -> 2250000 | AJ16: =AG16+V16*40*5 -> 760500 | AK16: =AJ16+AI16 -> 3010500
B17: Auxiliary Transformer A | C17: 110 | D17: 75000 | E17: 2 | F17: 75 | G17: 60000 | H17: 1 | I17: 1 | J17: =$C$3/G17 -> 0.13333333 | K17: =H17*I17*E17 -> 2 | L17: =J17*K17 -> 0.26666667 | M17: =L17*F17 -> 20 | N17: 10000 | O17: 1 | P17: 2 | Q17: =$C$3/N17 -> 0.8 | R17: =O17*$C$4*P17*E17 -> 32 | S17: =Q17*R17 -> 25.6 | T17: =S17*F17 -> 1920 | U17: =S17+L17 -> 25.866667 | V17: =T17+M17 -> 1940 | W17: *paired with rectifier setup. one upgrade serves | AI17: =D17*E17*5+AF17 -> 750000 | AJ17: =AG17+V17*40*5 -> 388000 | AK17: =AJ17+AI17 -> 1138000
B18: Auxiliary Transformer B | C18: 160 | D18: 100000 | G18: 80000 | H18: 0.5 | I18: 1 | J18: =$C$3/G18 -> 0.1 | K18: =H18*I18*E17 -> 1 | L18: =J18*K18 -> 0.1 | M18: =L18*F17 -> 7.5 | N18: 30000 | O18: 0.5 | P18: 2 | Q18: =$C$3/N18 -> 0.26666667 | R18: =O18*$C$4*P18*E17 -> 16 | S18: =Q18*R18 -> 4.2666667 | T18: =S18*F17 -> 320 | U18: =S18+L18 -> 4.3666667 | V18: =T18+M18 -> 327.5 | W18: *entire substation (both rectifier, auxiliary systems) | AI18: =D18*E17*5+AF18 -> 1000000 | AJ18: =AG18+V18*40*5 -> 65500 | AK18: =AJ18+AI18 -> 1065500
B19: Protection System A | C19: 175 | D19: 120000 | E19: 1 | F19: 100 | G19: 50000 | H19: 3 | I19: 2 | J19: =$C$3/G19 -> 0.16 | K19: =H19*I19*E19 -> 6 | L19: =J19*K19 -> 0.96 | M19: =L19*F19 -> 96 | N19: 25000 | O19: 3 | P19: 2 | Q19: =$C$3/N19 -> 0.32 | R19: =O19*$C$4*P19*E19 -> 48 | S19: =Q19*R19 -> 15.36 | T19: =S19*F19 -> 1536 | U19: =S19+L19 -> 16.32 | V19: =T19+M19 -> 1632 | AI19: =D19*E19*5+AF19 -> 600000 | AJ19: =AG19+V19*40*5 -> 326400 | AK19: =AJ19+AI19 -> 926400
B20: Protection System B | C20: 225 | D20: 270000 | G20: 120000 | H20: 3 | I20: 2 | J20: =$C$3/G20 -> 0.066666667 | K20: =H20*I20*E19 -> 6 | L20: =J20*K20 -> 0.4 | M20: =L20*F19 -> 40 | N20: 30000 | O20: 2 | P20: 2 | Q20: =$C$3/N20 -> 0.26666667 | R20: =O20*$C$4*P20*E19 -> 32 | S20: =Q20*R20 -> 8.5333333 | T20: =S20*F19 -> 853.33333 | U20: =S20+L20 -> 8.9333333 | V20: =T20+M20 -> 893.33333 | AI20: =D20*E19*5+AF20 -> 1350000 | AJ20: =AG20+V20*40*5 -> 178666.67 | AK20: =AJ20+AI20 -> 1528666.7
B21: Net Allocated Budget | C21: 750 | G21: 4600 | U21: 485 | AI21: 13500000 | AJ21: 5000000 | AK21: 18500000
C22: *total MTCE hrs/op hrs goal of 0.0606 ignored as it is same result as achieving 485 MTCE hrs/yr (via 485/8000 = 0.0606)
B25: SECTION 1.3: Shortlist Analysis
B27: Permutation | C27: Capability Index | D27: Costs and Hours Comparison | K27: Budget Consumption | M27: Replacement Delay Costs**
D28: Avg. MTBF | E28: Avg. MTCE hrs/year (all substations) | F28: Net MTCE hours | G28: Net MTCE cost | H28: Net CAPEX* | I28: Net OPEX | J28: Net LCC | K28: LCC Budget: £18.5m | M28: Add. MTCE cost** | N28: Add. Misc. cost** | P28: Remaining Budget after delay period
F29: (for 5 substations over 40 years) | M29: (to ensure operation reaches 42 years)
C30: CI | D30: operating hours | E30: operating hrs/year | F30: operating hrs/year | G30: £ | H30: £ | I30: £ | J30: £ | K30: % used | L30: remainder (£) | M30: £ | P30: £
B31: BAABB | C31: =C12+C13+C15+C18+C20 -> 753 | D31: =1/(1/G12+1/G13+1/G15+1/G18+1/G20) -> 3423.6805 | E31: =($U12+$U13+$U15+$U18+$U20)*5 -> 493.64118 | F31: =($U12+$U13+$U15+$U18+$U20)*5*40 -> 19745.647 | G31: =(V12+V13+V15+V18+V20)*5*40 -> 1525590.2 | H31: =AI12+AI13+AI15+AI18+AI20+25000 -> 13400000 | I31: =AJ12+AJ13+AJ15+AJ18+AJ20 -> 3255590.2 | J31: =AK12+AK13+AK15+AK18+AK20 -> 16630590 | K31: =(J31/J35) -> 0.89895082 | L31: =$J$35-J31 -> 1869409.8 | M31: =G31/20 -> 76279.51 | N31: 360000 | P31: =L31-M31-N31 -> 1433130.3
B32: BABBB | C32: =C12+C13+C16+C18+C20 -> 763 | D32: =1/(1/G12+1/G13+1/G16+1/G18+1/G20) -> 4606.5259 | E32: =(U12+U13+U16+U18+U20)*5 -> 461.14118 | F32: =(U12+U13+U16+U18+U20)*5*40 -> 18445.647 | G32: =(V12+V13+V16+V18+V20)*5*40 -> 1428090.2 | H32: =AI12+AI13+AI16+AI18+AI20+25000 -> 13700000 | I32: =AJ12+AJ13+AJ16+AJ18+AJ20 -> 2958090.2 | J32: =AK12+AK13+AK16+AK18+AK20 -> 16633090 | K32: =J32/J35 -> 0.89908596 | L32: =$J$35-J32 -> 1866909.8 | M32: =G32/20 -> 71404.51 | N32: =360000+50000 -> 410000 | P32: =L32-M32-N32 -> 1385505.3
B33: BBBBA | C33: =C12+C14+C16+C18+C19 -> 745 | D33: =1/(1/G12+1/G14+1/G16+1/G18+1/G19) -> 4502.8143 | E33: =($U12+$U14+$U16+$U18+$U19)*5 -> 496.86667 | F33: =($U12+$U14+$U16+$U18+$U19)*5*40 -> 19874.667 | G33: =(V12+V14+V16+V18+V19)*5*40 -> 1572200 | H33: =AI12+AI14+AI16+AI18+AI19+25000 -> 13450000 | I33: =AJ12+AJ14+AJ16+AJ18+AJ19 -> 3942200 | J33: =AK12+AK14+AK16+AK18+AK19 -> 17367200 | K33: =J33/J35 -> 0.93876757 | L33: =$J$35-J33 -> 1132800 | M33: =G33/20 -> 78610 | N33: =50000 -> 50000 | P33: =L33-M33-N33 -> 1004190
B34: BBBBB | C34: =C12+C14+C16+C18+C20 -> 795 | D34: =1/(1/G12+1/G14+1/G16+1/G18+1/G20) -> 4752.4752 | E34: =($U12+$U14+$U16+$U18+$U20)*5 -> 459.93333 | F34: =($U12+$U14+$U16+$U18+$U20)*5*40 -> 18397.333 | G34: =(V12+V14+V16+V18+V20)*5*40 -> 1424466.7 | H34: =AI12+AI14+AI16+AI18+AI20+25000 -> 14200000 | I34: =AJ12+AJ14+AJ16+AJ18+AJ20 -> 3794466.7 | J34: =AK12+AK14+AK16+AK18+AK20 -> 17969467 | K34: =J34/J35 -> 0.97132252 | L34: =$J$35-J34 -> 530533.33 | M34: =G34/20 -> 71223.333 | N34: 50000 | P34: =L34-M34-N34 -> 409310
B35: Allocated Budget | C35: =C21 -> 750 | D35: =G21 -> 4600 | E35: =U21 -> 485 | H35: =AI21 -> 13500000 | I35: =AJ21 -> 5000000 | J35: =AK21 -> 18500000
G36: *£25k added to CAPEX, accounting for commissioning engineer rated at £5k per substation | M36: *calculated to consider whether such costs fit in remaining budget

Sheet Permutations Analysis
B2: Capability Index (Budget: 750) | C2: Asset Type | E2: Value | F2: Permissible Permutations
F3: AAAAA | G3: AAAAB | H3: AABAA | I3: AABAB | J3: ABAAA | K3: ABAAB | L3: ABBAA | M3: ABBAB | N3: BAABA | O3: BAABB | P3: BABBA | Q3: BABBB | R3: BBABA | S3: BBABB | T3: BBBBA | U3: BBBBB
C4: RTx | D4: A | E4: ='Substation SE Figures'!C11 -> 105 | F4: =$E$4 -> 105 | G4: =$E$4 -> 105 | H4: =$E$4 -> 105 | I4: =$E$4 -> 105 | J4: =$E$4 -> 105 | K4: =$E$4 -> 105 | L4: =$E$4 -> 105 | M4: =$E$4 -> 105
D5: B | E5: ='Substation SE Figures'!C12 -> 140 | N5: =$E$5 -> 140 | O5: =$E$5 -> 140 | P5: =$E$5 -> 140 | Q5: =$E$5 -> 140 | R5: =$E$5 -> 140 | S5: =$E$5 -> 140 | T5: =$E$5 -> 140 | U5: =$E$5 -> 140
C6: HV switch | D6: A | E6: ='Substation SE Figures'!C13 -> 108 | F6: =$E$6 -> 108 | G6: =$E$6 -> 108 | H6: =$E$6 -> 108 | I6: =$E$6 -> 108 | N6: =$E$6 -> 108 | O6: =$E$6 -> 108 | P6: =$E$6 -> 108 | Q6: =$E$6 -> 108
D7: B | E7: ='Substation SE Figures'!C14 -> 140 | J7: =$E$7 -> 140 | K7: =$E$7 -> 140 | L7: =$E$7 -> 140 | M7: =$E$7 -> 140 | R7: =$E$7 -> 140 | S7: =$E$7 -> 140 | T7: =$E$7 -> 140 | U7: =$E$7 -> 140
C8: DC switch | D8: A | E8: ='Substation SE Figures'!C15 -> 120 | F8: =$E$8 -> 120 | G8: =$E$8 -> 120 | J8: =$E$8 -> 120 | K8: =$E$8 -> 120 | N8: =$E$8 -> 120 | O8: =$E$8 -> 120 | R8: =$E$8 -> 120 | S8: =$E$8 -> 120
D9: B | E9: ='Substation SE Figures'!C16 -> 130 | H9: =$E$9 -> 130 | I9: =$E$9 -> 130 | L9: =$E$9 -> 130 | M9: =$E$9 -> 130 | P9: =$E$9 -> 130 | Q9: =$E$9 -> 130 | T9: =$E$9 -> 130 | U9: =$E$9 -> 130
C10: ATx | D10: A | E10: ='Substation SE Figures'!C17 -> 110 | F10: =$E$10 -> 110 | G10: =$E$10 -> 110 | H10: =$E$10 -> 110 | I10: =$E$10 -> 110 | J10: =$E$10 -> 110 | K10: =$E$10 -> 110 | L10: =$E$10 -> 110 | M10: =$E$10 -> 110
D11: B | E11: ='Substation SE Figures'!C18 -> 160 | N11: =$E$11 -> 160 | O11: =$E$11 -> 160 | P11: =$E$11 -> 160 | Q11: =$E$11 -> 160 | R11: =$E$11 -> 160 | S11: =$E$11 -> 160 | T11: =$E$11 -> 160 | U11: =$E$11 -> 160
C12: Prot. Sys. | D12: A | E12: ='Substation SE Figures'!C19 -> 175 | F12: =$E$12 -> 175 | H12: 175 | J12: 175 | L12: 175 | N12: 175 | P12: 175 | R12: 175 | T12: 175
D13: B | E13: ='Substation SE Figures'!C20 -> 225 | G13: =$E$13 -> 225 | I13: =$E$13 -> 225 | K13: =$E$13 -> 225 | M13: =$E$13 -> 225 | O13: =$E$13 -> 225 | Q13: =$E$13 -> 225 | S13: =$E$13 -> 225 | U13: =$E$13 -> 225
B14: Cumulative CI (Highlight ≥ 745) | F14: =SUM(F4:F13) -> 618 | G14: =SUM(G4:G13) -> 668 | H14: =SUM(H4:H13) -> 628 | I14: =SUM(I4:I13) -> 678 | J14: =SUM(J4:J13) -> 650 | K14: =SUM(K4:K13) -> 700 | L14: =SUM(L4:L13) -> 660 | M14: =SUM(M4:M13) -> 710 | ... U14: =SUM(U4:U13) -> 795
B15: CAPEX (£) (Budget: £13.5m) | C15: RTx | D15: A | E15: ='Substation SE Figures'!AI11 -> 5000000 | F15: =$E15 -> 5000000 | G15: =$E15 -> 5000000 | H15: =$E15 -> 5000000 | I15: =$E15 -> 5000000 | J15: =$E15 -> 5000000 | K15: =$E15 -> 5000000 | L15: =$E15 -> 5000000 | M15: =$E15 -> 5000000
D16: B | E16: ='Substation SE Figures'!AI12 -> 7200000 | N16: =$E16 -> 7200000 | O16: =$E16 -> 7200000 | P16: =$E16 -> 7200000 | Q16: =$E16 -> 7200000 | R16: =$E16 -> 7200000 | S16: =$E16 -> 7200000 | T16: =$E16 -> 7200000 | U16: =$E16 -> 7200000
C17: HV switch | D17: A | E17: ='Substation SE Figures'!AI13 -> 1875000 | F17: =$E17 -> 1875000 | G17: =$E17 -> 1875000 | H17: =$E17 -> 1875000 | I17: =$E17 -> 1875000 | N17: =$E17 -> 1875000 | O17: =$E17 -> 1875000 | P17: =$E17 -> 1875000 | Q17: =$E17 -> 1875000
D18: B | E18: ='Substation SE Figures'!AI14 -> 2375000 | J18: =$E18 -> 2375000 | K18: =$E18 -> 2375000 | L18: =$E18 -> 2375000 | M18: =$E18 -> 2375000 | R18: =$E18 -> 2375000 | S18: =$E18 -> 2375000 | T18: =$E18 -> 2375000 | U18: =$E18 -> 2375000
C19: DC switch | D19: A | E19: ='Substation SE Figures'!AI15 -> 1950000 | F19: =$E19 -> 1950000 | G19: =$E19 -> 1950000 | J19: =$E19 -> 1950000 | K19: =$E19 -> 1950000 | N19: =$E19 -> 1950000 | O19: =$E19 -> 1950000 | R19: =$E19 -> 1950000 | S19: =$E19 -> 1950000
D20: B | E20: ='Substation SE Figures'!AI16 -> 2250000 | H20: =$E20 -> 2250000 | I20: =$E20 -> 2250000 | L20: =$E20 -> 2250000 | M20: =$E20 -> 2250000 | P20: =$E20 -> 2250000 | Q20: =$E20 -> 2250000 | T20: =$E20 -> 2250000 | U20: =$E20 -> 2250000
C21: ATx | D21: A | E21: ='Substation SE Figures'!AI17 -> 750000 | F21: =$E21 -> 750000 | G21: =$E21 -> 750000 | H21: =$E21 -> 750000 | I21: =$E21 -> 750000 | J21: =$E21 -> 750000 | K21: =$E21 -> 750000 | L21: =$E21 -> 750000 | M21: =$E21 -> 750000
D22: B | E22: ='Substation SE Figures'!AI18 -> 1000000 | N22: =$E22 -> 1000000 | O22: =$E22 -> 1000000 | P22: =$E22 -> 1000000 | Q22: =$E22 -> 1000000 | R22: =$E22 -> 1000000 | S22: =$E22 -> 1000000 | T22: =$E22 -> 1000000 | U22: =$E22 -> 1000000
C23: Prot. Sys. | D23: A | E23: ='Substation SE Figures'!AI19 -> 600000 | F23: =$E23 -> 600000 | H23: =$E23 -> 600000 | J23: =$E23 -> 600000 | L23: =$E23 -> 600000 | N23: =$E23 -> 600000 | P23: =$E23 -> 600000 | R23: =$E23 -> 600000 | T23: =$E23 -> 600000
D24: B | E24: ='Substation SE Figures'!AI20 -> 1350000 | G24: =$E24 -> 1350000 | I24: =$E24 -> 1350000 | K24: =$E24 -> 1350000 | M24: =$E24 -> 1350000 | O24: =$E24 -> 1350000 | Q24: =$E24 -> 1350000 | S24: =$E24 -> 1350000 | U24: =$E24 -> 1350000
B25: Cumulative CAPEX (Highlight ≤ £13.75m) | F25: =SUM(F15:F24) -> 10175000 | G25: =SUM(G15:G24) -> 10925000 | H25: =SUM(H15:H24) -> 10475000 | I25: =SUM(I15:I24) -> 11225000 | J25: =SUM(J15:J24) -> 10675000 | K25: =SUM(K15:K24) -> 11425000 | L25: =SUM(L15:L24) -> 10975000 | M25: =SUM(M15:M24) -> 11725000 | ... U25: =SUM(U15:U24) -> 14175000
B26: OPEX (£) (Budget: £5.0m) | C26: RTx | D26: A | E26: ='Substation SE Figures'!AJ11 -> 2226181.8 | F26: =$E26 -> 2226181.8 | G26: =$E26 -> 2226181.8 | H26: =$E26 -> 2226181.8 | I26: =$E26 -> 2226181.8 | J26: =$E26 -> 2226181.8 | K26: =$E26 -> 2226181.8 | L26: =$E26 -> 2226181.8 | M26: =$E26 -> 2226181.8
D27: B | E27: ='Substation SE Figures'!AJ12 -> 505800 | N27: =$E27 -> 505800 | O27: =$E27 -> 505800 | P27: =$E27 -> 505800 | Q27: =$E27 -> 505800 | R27: =$E27 -> 505800 | S27: =$E27 -> 505800 | T27: =$E27 -> 505800 | U27: =$E27 -> 505800
C28: HV switch | D28: A | E28: ='Substation SE Figures'!AJ13 -> 1447623.5 | F28: =$E28 -> 1447623.5 | G28: =$E28 -> 1447623.5 | H28: =$E28 -> 1447623.5 | I28: =$E28 -> 1447623.5 | N28: =$E28 -> 1447623.5 | O28: =$E28 -> 1447623.5 | P28: =$E28 -> 1447623.5 | Q28: =$E28 -> 1447623.5
D29: B | E29: ='Substation SE Figures'!AJ14 -> 2284000 | J29: =$E29 -> 2284000 | K29: =$E29 -> 2284000 | L29: =$E29 -> 2284000 | M29: =$E29 -> 2284000 | R29: =$E29 -> 2284000 | S29: =$E29 -> 2284000 | T29: =$E29 -> 2284000 | U29: =$E29 -> 2284000
C30: DC switch | D30: A | E30: ='Substation SE Figures'!AJ15 -> 1058000 | F30: =$E30 -> 1058000 | G30: =$E30 -> 1058000 | J30: =$E30 -> 1058000 | K30: =$E30 -> 1058000 | N30: =$E30 -> 1058000 | O30: =$E30 -> 1058000 | R30: =$E30 -> 1058000 | S30: =$E30 -> 1058000
D31: B | E31: ='Substation SE Figures'!AJ16 -> 760500 | H31: =$E31 -> 760500 | I31: =$E31 -> 760500 | L31: =$E31 -> 760500 | M31: =$E31 -> 760500 | P31: =$E31 -> 760500 | Q31: =$E31 -> 760500 | T31: =$E31 -> 760500 | U31: =$E31 -> 760500
C32: ATx | D32: A | E32: ='Substation SE Figures'!AJ17 -> 388000 | F32: =$E32 -> 388000 | G32: =$E32 -> 388000 | H32: =$E32 -> 388000 | I32: =$E32 -> 388000 | J32: =$E32 -> 388000 | K32: =$E32 -> 388000 | L32: =$E32 -> 388000 | M32: =$E32 -> 388000
D33: B | E33: ='Substation SE Figures'!AJ18 -> 65500 | N33: =$E33 -> 65500 | O33: =$E33 -> 65500 | P33: =$E33 -> 65500 | Q33: =$E33 -> 65500 | R33: =$E33 -> 65500 | S33: =$E33 -> 65500 | T33: =$E33 -> 65500 | U33: =$E33 -> 65500
C34: Prot. Sys. | D34: A | E34: ='Substation SE Figures'!AJ19 -> 326400 | F34: =$E34 -> 326400 | H34: =$E34 -> 326400 | J34: =$E34 -> 326400 | L34: =$E34 -> 326400 | N34: =$E34 -> 326400 | P34: =$E34 -> 326400 | R34: =$E34 -> 326400 | T34: =$E34 -> 326400
D35: B | E35: ='Substation SE Figures'!AJ20 -> 178666.67 | G35: =$E35 -> 178666.67 | I35: =$E35 -> 178666.67 | K35: =$E35 -> 178666.67 | M35: =$E35 -> 178666.67 | O35: =$E35 -> 178666.67 | Q35: =$E35 -> 178666.67 | S35: =$E35 -> 178666.67 | U35: =$E35 -> 178666.67
B36: Cumulative OPEX (Highlight ≤ £5.25m) | F36: =SUM(F26:F35) -> 5446205.3 | G36: =SUM(G26:G35) -> 5298472 | H36: =SUM(H26:H35) -> 5148705.3 | I36: =SUM(I26:I35) -> 5000972 | J36: =SUM(J26:J35) -> 6282581.8 | K36: =SUM(K26:K35) -> 6134848.5 | L36: =SUM(L26:L35) -> 5985081.8 | M36: =SUM(M26:M35) -> 5837348.5 | ... U36: =SUM(U26:U35) -> 3794466.7
B38: Net LCC per permutation (£) (Budget: £18.5m) | F38: =SUM(F36+F25) -> 15621205 | G38: =SUM(G36+G25) -> 16223472 | H38: =SUM(H36+H25) -> 15623705 | I38: =SUM(I36+I25) -> 16225972 | J38: =SUM(J36+J25) -> 16957582 | K38: =SUM(K36+K25) -> 17559848 | L38: =SUM(L36+L25) -> 16960082 | M38: =SUM(M36+M25) -> 17562348 | ... U38: =SUM(U36+U25) -> 17969467
